file_genie/__init__.py
file_genie/enums/FilterType.py
file_genie/enums/LogLevel.py
file_genie/enums/ParsedDataResponseType.py
file_genie/exceptions/expcetion.py
file_genie/service/file_parser.py
file_genie/utils/common_utils.py
file_genie/utils/file_parser_constants.py
file_genie/utils/logger.py
file_genie/utils/mt940_utils.py
file_genie/utils/s3_file_parser.py
file_genie-0.0.4.dist-info/METADATA
file_genie-0.0.4.dist-info/WHEEL
file_genie-0.0.4.dist-info/top_level.txt
file_genie-0.0.4.dist-info/RECORD
